pymysqlreplication/__init__.py
pymysqlreplication/_compat.py
pymysqlreplication/binlogstream.py
pymysqlreplication/bitmap.py
pymysqlreplication/column.py
pymysqlreplication/event.py
pymysqlreplication/exceptions.py
pymysqlreplication/gtid.py
pymysqlreplication/packet.py
pymysqlreplication/row_event.py
pymysqlreplication/table.py
pymysqlreplication/constants/BINLOG.py
pymysqlreplication/constants/FIELD_TYPE.py
pymysqlreplication/constants/STATUS_VAR_KEY.py
pymysqlreplication/constants/__init__.py
pymysqlreplication/tests/__init__.py
pymysqlreplication/tests/base.py
pymysqlreplication/tests/benchmark.py
pymysqlreplication/tests/binlogfilereader.py
pymysqlreplication/tests/test_abnormal.py
pymysqlreplication/tests/test_basic.py
pymysqlreplication/tests/test_data_objects.py
pymysqlreplication/tests/test_data_type.py
tokko_mysql_replication_custom-0.1.1.dist-info/METADATA
tokko_mysql_replication_custom-0.1.1.dist-info/WHEEL
tokko_mysql_replication_custom-0.1.1.dist-info/top_level.txt
tokko_mysql_replication_custom-0.1.1.dist-info/RECORD
